{
  "query": "plumber, 36547, Gulf Shores, AL, US",
  "name": "Graham Plumbing Repair",
  "name_for_emails": "Graham Plumbing Repair",
  "site": NaN,
  "subtypes": "Plumber, Service establishment",
  "category": "Plumber",
  "type": "Plumber",
  "phone": "+1 251-979-6026",
  "phone.phones_enricher.carrier_name": "CELLCO PARTNERSHIP DBA VERIZON WIRELESS - AL",
  "phone.phones_enricher.carrier_type": "mobile",
  "full_address": NaN,
  "borough": NaN,
  "street": NaN,
  "city": NaN,
  "postal_code": NaN,
  "state": NaN,
  "us_state": NaN,
  "country": NaN,
  "country_code": NaN,
  "latitude": 30.4681706,
  "longitude": -87.7064702,
  "h3": "894450531a7ffff",
  "time_zone": "America/Chicago",
  "plus_code": NaN,
  "area_service": true,
  "rating": 5.0,
  "reviews": 3.0,
  "reviews_link": NaN,
  "reviews_tags": NaN,
  "reviews_per_score": NaN,
  "reviews_per_score_1": 0.0,
  "reviews_per_score_2": 0.0,
  "reviews_per_score_3": 0.0,
  "reviews_per_score_4": 0.0,
  "reviews_per_score_5": 3.0,
  "photos_count": NaN,
  "photo": NaN,
  "street_view": NaN,
  "located_in": NaN,
  "working_hours": {
    "Monday": "8AM-5PM",
    "Tuesday": "8AM-5PM",
    "Wednesday": "8AM-5PM",
    "Thursday": "8AM-5PM",
    "Friday": "8AM-5PM",
    "Saturday": "Closed",
    "Sunday": "Closed"
  },
  "working_hours_old_format": "Monday:8AM-5PM|Tuesday:8AM-5PM|Wednesday:8AM-5PM|Thursday:8AM-5PM|Friday:8AM-5PM|Saturday:Closed|Sunday:Closed",
  "other_hours": NaN,
  "popular_times": NaN,
  "business_status": "OPERATIONAL",
  "about": "{\"Payments\": {\"Cash-only\": true}}",
  "range": NaN,
  "posts": NaN,
  "logo": "https://lh4.googleusercontent.com/-1UGq4LWg7Mw/AAAAAAAAAAI/AAAAAAAAAAA/RJ6sBm_76VM/photo.jpg",
  "description": NaN,
  "typical_time_spent": NaN,
  "verified": true,
  "owner_id": "118253672002236375953",
  "owner_title": "Graham Plumbing Repair",
  "owner_link": "https://www.google.com/maps/contrib/118253672002236375953",
  "reservation_links": NaN,
  "booking_appointment_link": NaN,
  "menu_link": NaN,
  "order_links": NaN,
  "location_link": "https://www.google.com/maps/place/Graham+Plumbing+Repair/@30.468170599999997,-87.7064702,14z/data=!4m8!1m2!2m1!1sGraham+Plumbing+Repair!3m4!1s0x889a13eeaded8d53:0x4f6d1385366cb72f!8m2!3d30.468170599999997!4d-87.7064702",
  "location_reviews_link": "https://www.google.com/maps/place/Graham+Plumbing+Repair/@30.468170599999997,-87.7064702,13.99z/data=!4m16!1m7!3m6!1s0x889a13eeaded8d53:0x4f6d1385366cb72f!2sGraham+Plumbing+Repair!8m2!3d30.468170599999997!4d-87.7064702!16s%2Fg%2F11ckvg1dmb!3m7!1s0x889a13eeaded8d53:0x4f6d1385366cb72f!8m2!3d30.468170599999997!4d-87.7064702!9m1!1b1!16s%2Fg%2F11ckvg1dmb?entry=ttu",
  "place_id": "ChIJU43tre4TmogRL7dsNoUTbU8",
  "google_id": "0x889a13eeaded8d53:0x4f6d1385366cb72f",
  "cid": 5.72325e+18,
  "kgmid": "/g/11j8p67b8n",
  "reviews_id": NaN,
  "located_google_id": NaN,
  "email_1": "support@grahamplumbingservices.com",
  "email_1.emails_validator.status": "RECEIVING",
  "email_1.emails_validator.status_details": "SMTP validated",
  "email_1_full_name": NaN,
  "email_1_first_name": NaN,
  "email_1_last_name": NaN,
  "email_1_title": NaN,
  "email_1_phone": NaN,
  "email_2": NaN,
  "email_2.emails_validator.status": NaN,
  "email_2.emails_validator.status_details": NaN,
  "email_2_full_name": NaN,
  "email_2_first_name": NaN,
  "email_2_last_name": NaN,
  "email_2_title": NaN,
  "email_2_phone": NaN,
  "email_3": NaN,
  "email_3.emails_validator.status": NaN,
  "email_3.emails_validator.status_details": NaN,
  "email_3_full_name": NaN,
  "email_3_first_name": NaN,
  "email_3_last_name": NaN,
  "email_3_title": NaN,
  "email_3_phone": NaN,
  "phone_1": "+1 281-302-6710",
  "phone_1.phones_enricher.carrier_name": "COMCAST IP PHONE, LLC",
  "phone_1.phones_enricher.carrier_type": "voip",
  "phone_2": NaN,
  "phone_3": NaN,
  "facebook": "https://www.facebook.com/GrahamPlumbingServices/",
  "instagram": NaN,
  "linkedin": NaN,
  "tiktok": NaN,
  "medium": NaN,
  "reddit": NaN,
  "skype": NaN,
  "snapchat": NaN,
  "telegram": NaN,
  "whatsapp": NaN,
  "twitter": NaN,
  "vimeo": NaN,
  "youtube": NaN,
  "github": NaN,
  "crunchbase": NaN,
  "website_title": NaN,
  "website_generator": NaN,
  "website_description": NaN,
  "website_keywords": NaN,
  "website_has_fb_pixel": NaN,
  "website_has_google_tag": NaN,
  "primarycolor": "#4474e4",
  "secondarycolor": "#133585"
}